{
    "name": "aageyev-nodejs",
    "version": "0.1.3",
    "author": "Andrii Ageiev",
    "summary": "Install stable NodeJs",
    "license": "MIT",
    "source": "https://bitbucket.org/aageyev/nodejs",
    "project_page": "https://bitbucket.org/aageyev/nodejs/wiki/Home",
    "issues_url": "https://bitbucket.org/aageyev/nodejs/issues",
    "dependencies": [
        {
            "name": "puppetlabs-apt",
            "version_requirement": ">= 1.7.0"
        },
        {
            "name": "stahnma-epel",
            "version_requirement": ">= 1.1.1"
        }
    ]
}
